[
  {
    "en": "word2-301",
    "phon": "/wɜːrd/",
    "cn": "身体43"
  },
  {
    "en": "word2-302",
    "phon": "/wɜːrd/",
    "cn": "学校44"
  },
  {
    "en": "word2-303",
    "phon": "/wɜːrd/",
    "cn": "动作44"
  },
  {
    "en": "word2-304",
    "phon": "/wɜːrd/",
    "cn": "时间44"
  },
  {
    "en": "word2-305",
    "phon": "/wɜːrd/",
    "cn": "自然44"
  },
  {
    "en": "word2-306",
    "phon": "/wɜːrd/",
    "cn": "动物44"
  },
  {
    "en": "word2-307",
    "phon": "/wɜːrd/",
    "cn": "食物44"
  },
  {
    "en": "word2-308",
    "phon": "/wɜːrd/",
    "cn": "身体44"
  },
  {
    "en": "word2-309",
    "phon": "/wɜːrd/",
    "cn": "学校45"
  },
  {
    "en": "word2-310",
    "phon": "/wɜːrd/",
    "cn": "动作45"
  },
  {
    "en": "word2-311",
    "phon": "/wɜːrd/",
    "cn": "时间45"
  },
  {
    "en": "word2-312",
    "phon": "/wɜːrd/",
    "cn": "自然45"
  },
  {
    "en": "word2-313",
    "phon": "/wɜːrd/",
    "cn": "动物45"
  },
  {
    "en": "word2-314",
    "phon": "/wɜːrd/",
    "cn": "食物45"
  },
  {
    "en": "word2-315",
    "phon": "/wɜːrd/",
    "cn": "身体45"
  },
  {
    "en": "word2-316",
    "phon": "/wɜːrd/",
    "cn": "学校46"
  },
  {
    "en": "word2-317",
    "phon": "/wɜːrd/",
    "cn": "动作46"
  },
  {
    "en": "word2-318",
    "phon": "/wɜːrd/",
    "cn": "时间46"
  },
  {
    "en": "word2-319",
    "phon": "/wɜːrd/",
    "cn": "自然46"
  },
  {
    "en": "word2-320",
    "phon": "/wɜːrd/",
    "cn": "动物46"
  },
  {
    "en": "word2-321",
    "phon": "/wɜːrd/",
    "cn": "食物46"
  },
  {
    "en": "word2-322",
    "phon": "/wɜːrd/",
    "cn": "身体46"
  },
  {
    "en": "word2-323",
    "phon": "/wɜːrd/",
    "cn": "学校47"
  },
  {
    "en": "word2-324",
    "phon": "/wɜːrd/",
    "cn": "动作47"
  },
  {
    "en": "word2-325",
    "phon": "/wɜːrd/",
    "cn": "时间47"
  },
  {
    "en": "word2-326",
    "phon": "/wɜːrd/",
    "cn": "自然47"
  },
  {
    "en": "word2-327",
    "phon": "/wɜːrd/",
    "cn": "动物47"
  },
  {
    "en": "word2-328",
    "phon": "/wɜːrd/",
    "cn": "食物47"
  },
  {
    "en": "word2-329",
    "phon": "/wɜːrd/",
    "cn": "身体47"
  },
  {
    "en": "word2-330",
    "phon": "/wɜːrd/",
    "cn": "学校48"
  },
  {
    "en": "word2-331",
    "phon": "/wɜːrd/",
    "cn": "动作48"
  },
  {
    "en": "word2-332",
    "phon": "/wɜːrd/",
    "cn": "时间48"
  },
  {
    "en": "word2-333",
    "phon": "/wɜːrd/",
    "cn": "自然48"
  },
  {
    "en": "word2-334",
    "phon": "/wɜːrd/",
    "cn": "动物48"
  },
  {
    "en": "word2-335",
    "phon": "/wɜːrd/",
    "cn": "食物48"
  },
  {
    "en": "word2-336",
    "phon": "/wɜːrd/",
    "cn": "身体48"
  },
  {
    "en": "word2-337",
    "phon": "/wɜːrd/",
    "cn": "学校49"
  },
  {
    "en": "word2-338",
    "phon": "/wɜːrd/",
    "cn": "动作49"
  },
  {
    "en": "word2-339",
    "phon": "/wɜːrd/",
    "cn": "时间49"
  },
  {
    "en": "word2-340",
    "phon": "/wɜːrd/",
    "cn": "自然49"
  },
  {
    "en": "word2-341",
    "phon": "/wɜːrd/",
    "cn": "动物49"
  },
  {
    "en": "word2-342",
    "phon": "/wɜːrd/",
    "cn": "食物49"
  },
  {
    "en": "word2-343",
    "phon": "/wɜːrd/",
    "cn": "身体49"
  },
  {
    "en": "word2-344",
    "phon": "/wɜːrd/",
    "cn": "学校50"
  },
  {
    "en": "word2-345",
    "phon": "/wɜːrd/",
    "cn": "动作50"
  },
  {
    "en": "word2-346",
    "phon": "/wɜːrd/",
    "cn": "时间50"
  },
  {
    "en": "word2-347",
    "phon": "/wɜːrd/",
    "cn": "自然50"
  },
  {
    "en": "word2-348",
    "phon": "/wɜːrd/",
    "cn": "动物50"
  },
  {
    "en": "word2-349",
    "phon": "/wɜːrd/",
    "cn": "食物50"
  },
  {
    "en": "word2-350",
    "phon": "/wɜːrd/",
    "cn": "身体50"
  }
]