[
  {
    "en": "charge",
    "phon": "/tʃɑːdʒ/",
    "cn": "收费"
  },
  {
    "en": "cheer",
    "phon": "/tʃɪər/",
    "cn": "欢呼"
  },
  {
    "en": "choice",
    "phon": "/tʃɔɪs/",
    "cn": "选择"
  },
  {
    "en": "citizen",
    "phon": "/ˈsɪt.ɪ.zən/",
    "cn": "公民"
  },
  {
    "en": "comfortable",
    "phon": "/ˈkʌmf.tə.bəl/",
    "cn": "舒适的"
  },
  {
    "en": "command",
    "phon": "/kəˈmɑːnd/",
    "cn": "命令"
  },
  {
    "en": "common",
    "phon": "/ˈkɒm.ən/",
    "cn": "共同的"
  },
  {
    "en": "compare",
    "phon": "/kəmˈpeər/",
    "cn": "比较"
  },
  {
    "en": "compete",
    "phon": "/kəmˈpiːt/",
    "cn": "竞争"
  },
  {
    "en": "complete",
    "phon": "/kəmˈpliːt/",
    "cn": "完成"
  },
  {
    "en": "concern",
    "phon": "/kənˈsɜːn/",
    "cn": "关心"
  },
  {
    "en": "condition",
    "phon": "/kənˈdɪʃ.ən/",
    "cn": "条件"
  },
  {
    "en": "confidence",
    "phon": "/ˈkɒn.fɪ.dəns/",
    "cn": "信心"
  },
  {
    "en": "connect",
    "phon": "/kəˈnekt/",
    "cn": "连接"
  },
  {
    "en": "consider",
    "phon": "/kənˈsɪd.ər/",
    "cn": "考虑"
  },
  {
    "en": "contain",
    "phon": "/kənˈteɪn/",
    "cn": "包含"
  },
  {
    "en": "continue",
    "phon": "/kənˈtɪn.juː/",
    "cn": "继续"
  },
  {
    "en": "control",
    "phon": "/kənˈtrəʊl/",
    "cn": "控制"
  },
  {
    "en": "convenient",
    "phon": "/kənˈviː.ni.ənt/",
    "cn": "方便的"
  },
  {
    "en": "conversation",
    "phon": "/ˌkɒn.vəˈseɪ.ʃən/",
    "cn": "对话"
  },
  {
    "en": "impervious",
    "phon": "/ɪmˈpɜːr.vi.əs/",
    "cn": "不受影响的"
  },
  {
    "en": "courage",
    "phon": "/ˈkʌr.ɪdʒ/",
    "cn": "勇气"
  },
  {
    "en": "curious",
    "phon": "/ˈkjʊər.i.əs/",
    "cn": "好奇的"
  },
  {
    "en": "custom",
    "phon": "/ˈkʌs.təm/",
    "cn": "习俗"
  },
  {
    "en": "debate",
    "phon": "/dɪˈbeɪt/",
    "cn": "辩论"
  },
  {
    "en": "decide",
    "phon": "/dɪˈsaɪd/",
    "cn": "决定"
  },
  {
    "en": "demand",
    "phon": "/dɪˈmɑːnd/",
    "cn": "需求"
  },
  {
    "en": "depend",
    "phon": "/dɪˈpend/",
    "cn": "依赖"
  },
  {
    "en": "describe",
    "phon": "/dɪˈskraɪb/",
    "cn": "描述"
  },
  {
    "en": "design",
    "phon": "/dɪˈzaɪn/",
    "cn": "设计"
  },
  {
    "en": "destroy",
    "phon": "/dɪˈstrɔɪ/",
    "cn": "破坏"
  },
  {
    "en": "develop",
    "phon": "/dɪˈvel.əp/",
    "cn": "发展"
  },
  {
    "en": "devote",
    "phon": "/dɪˈvəʊt/",
    "cn": "奉献"
  },
  {
    "en": "direction",
    "phon": "/dəˈrek.ʃən/",
    "cn": "方向"
  },
  {
    "en": "discover",
    "phon": "/dɪsˈkʌv.ər/",
    "cn": "发现"
  },
  {
    "en": "discuss",
    "phon": "/dɪˈskʌs/",
    "cn": "讨论"
  },
  {
    "en": "distance",
    "phon": "/ˈdɪs.təns/",
    "cn": "距离"
  },
  {
    "en": "divide",
    "phon": "/dɪˈvaɪd/",
    "cn": "分开"
  },
  {
    "en": "donate",
    "phon": "/dəʊˈneɪt/",
    "cn": "捐赠"
  },
  {
    "en": "double",
    "phon": "/ˈdʌb.əl/",
    "cn": "双倍"
  },
  {
    "en": "doubt",
    "phon": "/daʊt/",
    "cn": "怀疑"
  },
  {
    "en": "eager",
    "phon": "/ˈiː.ɡər/",
    "cn": "渴望的"
  },
  {
    "en": "effect",
    "phon": "/ɪˈfekt/",
    "cn": "效果"
  },
  {
    "en": "effort",
    "phon": "/ˈef.ət/",
    "cn": "努力"
  },
  {
    "en": "enable",
    "phon": "/ɪˈneɪ.bəl/",
    "cn": "使能够"
  },
  {
    "en": "encourage",
    "phon": "/ɪnˈkʌr.ɪdʒ/",
    "cn": "鼓励"
  },
  {
    "en": "enemy",
    "phon": "/ˈen.ə.mi/",
    "cn": "敌人"
  },
  {
    "en": "energy",
    "phon": "/ˈen.ə.dʒi/",
    "cn": "能量"
  },
  {
    "en": "enjoy",
    "phon": "/ɪnˈdʒɔɪ/",
    "cn": "享受"
  },
  {
    "en": "impetuous",
    "phon": "/ɪmˈpetʃ.u.əs/",
    "cn": "冲动的"
  }
]